{"id":"ekstep.learning.item.read","ver":"1.0","ts":"2018-10-17T02:12:56ZZ","params":{"resmsgid":"83068fdc-bd4f-4549-aa64-f2dd99377aee","msgid":null,"err":null,"status":"successful","errmsg":null},"responseCode":"OK","result":{"assessment_item":{"template":"NA","itemType":"UNIT","code":"NA","subject":"Social Science","qlevel":"EASY","channel":"01241408242723225614","language":["English"],"medium":"Hindi","title":"राज्यों को उनकी राजधानियों से सम्मलित कीजिये \n","type":"mtf","body":"{\"data\":{\"plugin\":{\"id\":\"org.ekstep.questionunit.mtf\",\"version\":\"1.0\",\"templateId\":\"horizontalMTF\"},\"data\":{\"question\":{\"text\":\"<p>राज्यों को उनकी राजधानियों से सम्मलित कीजिये&nbsp;</p>\\n\",\"image\":\"\",\"audio\":\"\",\"hint\":\"\"},\"option\":{\"optionsLHS\":[{\"text\":\"राजस्थान\",\"image\":\"\",\"audio\":\"\",\"hint\":\"\",\"index\":1,\"$$hashKey\":\"object:1829\"},{\"text\":\"उत्तर प्रदेश\",\"image\":\"\",\"audio\":\"\",\"hint\":\"\",\"index\":2,\"$$hashKey\":\"object:1830\"},{\"text\":\"मध्यप्रदेश\",\"image\":\"\",\"audio\":\"\",\"hint\":\"\",\"index\":3,\"$$hashKey\":\"object:1831\"},{\"text\":\"गुजरात\",\"image\":\"\",\"audio\":\"\",\"hint\":\"\",\"index\":4,\"$$hashKey\":\"object:1849\"}],\"optionsRHS\":[{\"text\":\"जयपुर\",\"image\":\"\",\"audio\":\"\",\"hint\":\"\",\"mapIndex\":1},{\"text\":\"लखनऊ\",\"image\":\"\",\"audio\":\"\",\"hint\":\"\",\"mapIndex\":2},{\"text\":\"भोपाल\",\"image\":\"\",\"audio\":\"\",\"hint\":\"\",\"mapIndex\":3},{\"text\":\"गांधीनगर\",\"image\":\"\",\"audio\":\"\",\"hint\":\"\",\"mapIndex\":4}],\"questionCount\":0},\"media\":[]},\"config\":{\"metadata\":{\"name\":\"राज्यों को उनकी राजधानियों से सम्मलित कीजिये \\n\",\"medium\":\"Hindi\",\"level\":\"EASY\",\"max_score\":6,\"gradeLevel\":[\"Class 7\"],\"topic\":[\"Road Safety Education\"],\"subject\":\"Social Science\",\"board\":\"State (Rajasthan)\",\"category\":\"MTF\"},\"max_time\":0,\"max_score\":1,\"partial_scoring\":false,\"layout\":\"Horizontal\",\"isShuffleOption\":false,\"questionCount\":1},\"media\":[]}}","createdOn":"2018-08-09T05:53:43.910+0000","gradeLevel":["Class 7"],"isShuffleOption":false,"appId":"prod.diksha.portal","lastUpdatedOn":"2018-08-09T05:53:43.910+0000","rhs_options":[{"value":{"type":"mixed","text":"इक","image":"","count":"","audio":"","resvalue":"इक","resindex":0},"index":0}],"identifier":"do_31256484064387891218251","question":"<p>राज्यों को उनकी राजधानियों से सम्मलित कीजिये&nbsp;</p>\n","consumerId":"0aa13c48-dda0-4259-9007-c795dacd7b9c","version":2,"versionKey":"1533794023910","lhs_options":[{"value":{"type":"mixed","text":"इक","image":"","count":"","audio":"","resvalue":"इक","resindex":0},"index":0}],"framework":"rj_k-12","createdBy":"d9798304-044b-4afb-a4b1-c77c8b56ae38","max_score":1,"name":"राज्यों को उनकी राजधानियों से सम्मलित कीजिये \n","topic":["Road Safety Education"],"template_id":"NA","category":"MTF","board":"State (Rajasthan)","status":"Live"}}}