{"id":"ekstep.learning.item.read","ver":"1.0","ts":"2018-10-17T02:13:16ZZ","params":{"resmsgid":"71cba9f4-a362-4169-b095-296291415c18","msgid":null,"err":null,"status":"successful","errmsg":null},"responseCode":"OK","result":{"assessment_item":{"template":"NA","itemType":"UNIT","code":"NA","subject":"English","qlevel":"MEDIUM","channel":"01235953109336064029450","language":["English"],"medium":"English","type":"mtf","title":"Copy of - Match the following in order to make sense.\n","body":"{\"data\":{\"plugin\":{\"id\":\"org.ekstep.questionunit.mtf\",\"version\":\"1.0\",\"templateId\":\"horizontalMTF\"},\"data\":{\"question\":{\"text\":\"<p>Match the following in order to make sense.</p>\\n\",\"image\":\"\",\"audio\":\"\",\"audioName\":\"\",\"hint\":\"\"},\"option\":{\"optionsLHS\":[{\"text\":\"Dog\",\"image\":\"/assets/public//content/1467016089645dog.png\",\"audio\":\"\",\"audioName\":\"\",\"hint\":\"\",\"index\":1,\"$$hashKey\":\"object:2609\"},{\"text\":\"Rabbit\",\"image\":\"/assets/public//content/do_31244463989519974425156/artifact/assetsrabbit1_4303_1519121080_1519121081263.png\",\"audio\":\"\",\"audioName\":\"\",\"hint\":\"\",\"index\":2,\"$$hashKey\":\"object:2610\"},{\"text\":\"Lion\",\"image\":\"/assets/public//content/1467098446095lion.png\",\"audio\":\"\",\"audioName\":\"\",\"hint\":\"\",\"index\":3,\"$$hashKey\":\"object:2611\"},{\"text\":\"Bird\",\"image\":\"/assets/public//content/do_31221744228700979214822/artifact/crow_1491386998256.png\",\"audio\":\"\",\"audioName\":\"\",\"hint\":\"\",\"index\":4,\"$$hashKey\":\"object:2641\"}],\"optionsRHS\":[{\"text\":\"Canal\",\"image\":\"\",\"audio\":\"\",\"audioName\":\"\",\"hint\":\"\",\"mapIndex\":1},{\"text\":\"Burrow\",\"image\":\"\",\"audio\":\"\",\"audioName\":\"\",\"hint\":\"\",\"mapIndex\":2},{\"text\":\"Den\",\"image\":\"\",\"audio\":\"\",\"audioName\":\"\",\"hint\":\"\",\"mapIndex\":3},{\"text\":\"Nest\",\"image\":\"\",\"audio\":\"\",\"audioName\":\"\",\"hint\":\"\",\"mapIndex\":4}],\"questionCount\":0},\"media\":[{\"id\":579522517,\"src\":\"/assets/public//content/1467016089645dog.png\",\"assetId\":\"do_30019821_dogImage\",\"type\":\"image\",\"preload\":false},{\"id\":330773160,\"src\":\"/assets/public//content/do_31244463989519974425156/artifact/assetsrabbit1_4303_1519121080_1519121081263.png\",\"assetId\":\"do_31244463989519974425156\",\"type\":\"image\",\"preload\":false},{\"id\":81197763,\"src\":\"/assets/public//content/1467098446095lion.png\",\"assetId\":\"do_30021668_lionImage\",\"type\":\"image\",\"preload\":false},{\"id\":588741685,\"src\":\"/assets/public//content/do_31221744228700979214822/artifact/crow_1491386998256.png\",\"assetId\":\"do_31221744228700979214822\",\"type\":\"image\",\"preload\":false}]},\"config\":{\"metadata\":{\"questionMaxScore\":1,\"isShuffleOption\":false,\"isPartialScore\":true,\"templateType\":\"Horizontal\",\"name\":\"Match the following in order to make sense.\\n\",\"title\":\"Copy of - Match the following in order to make sense.\\n\",\"qlevel\":\"EASY\",\"subject\":\"English\",\"topic\":[],\"max_score\":1,\"concepts\":[{\"identifier\":\"LO52\",\"name\":\"More Than One Meaning\"}],\"board\":\"State (Tamil Nadu)\",\"gradeLevel\":[\"Class 1\"],\"medium\":\"English\",\"category\":\"MTF\"},\"max_time\":0,\"max_score\":1,\"partial_scoring\":true,\"layout\":\"Horizontal\",\"isShuffleOption\":false,\"questionCount\":1},\"media\":[{\"id\":579522517,\"src\":\"/assets/public//content/1467016089645dog.png\",\"assetId\":\"do_30019821_dogImage\",\"type\":\"image\",\"preload\":false},{\"id\":330773160,\"src\":\"/assets/public//content/do_31244463989519974425156/artifact/assetsrabbit1_4303_1519121080_1519121081263.png\",\"assetId\":\"do_31244463989519974425156\",\"type\":\"image\",\"preload\":false},{\"id\":81197763,\"src\":\"/assets/public//content/1467098446095lion.png\",\"assetId\":\"do_30021668_lionImage\",\"type\":\"image\",\"preload\":false},{\"id\":588741685,\"src\":\"/assets/public//content/do_31221744228700979214822/artifact/crow_1491386998256.png\",\"assetId\":\"do_31221744228700979214822\",\"type\":\"image\",\"preload\":false}]}}","createdOn":"2018-09-18T05:43:18.520+0000","gradeLevel":["Class 1"],"isShuffleOption":false,"appId":"prod.diksha.portal","lastUpdatedOn":"2018-09-18T05:43:18.520+0000","rhs_options":[{"value":{"type":"mixed","text":"इक","image":"","count":"","audio":"","resvalue":"इक","resindex":0},"index":0}],"identifier":"do_312593147072675840222843","question":"<p>Match the following in order to make sense.</p>\n","consumerId":"0aa13c48-dda0-4259-9007-c795dacd7b9c","version":2,"versionKey":"1537249398520","lhs_options":[{"value":{"type":"mixed","text":"इक","image":"","count":"","audio":"","resvalue":"इक","resindex":0},"index":0}],"framework":"NCF","concepts":[{"identifier":"LO52","name":"More Than One Meaning","objectType":"Concept","relation":"associatedTo","description":null,"index":null,"status":null,"depth":null,"mimeType":null,"visibility":null,"compatibilityLevel":null}],"createdBy":"9dfba19a-3c57-4b9c-8ac0-1894126d7d75","max_score":1,"name":"Copy of - Match the following in order to make sense.\n","template_id":"NA","category":"MTF","board":"State (Tamil Nadu)","status":"Live"}}}