{"id":"ekstep.learning.item.read","ver":"1.0","ts":"2018-10-17T02:13:33ZZ","params":{"resmsgid":"a8e73084-6512-405b-9ed5-358cf2af5e1d","msgid":null,"err":null,"status":"successful","errmsg":null},"responseCode":"OK","result":{"assessment_item":{"template":"NA","templateType":"Horizontal","isPartialScore":true,"itemType":"UNIT","code":"NA","subject":"Telugu","qlevel":"MEDIUM","channel":"in.ekstep","language":["English"],"medium":"Hindi","type":"mtf","title":"test2.1.8\n","body":"{\"data\":{\"plugin\":{\"id\":\"org.ekstep.questionunit.mtf\",\"version\":\"1.1\",\"templateId\":\"horizontalMTF\"},\"data\":{\"question\":{\"text\":\"<p>test2.1.8</p>\\n\",\"image\":\"\",\"audio\":\"\",\"audioName\":\"\",\"hint\":\"\"},\"option\":{\"optionsLHS\":[{\"text\":\"1\",\"image\":\"\",\"audio\":\"\",\"audioName\":\"\",\"hint\":\"\",\"index\":1,\"$$hashKey\":\"object:3008\"},{\"text\":\"2\",\"image\":\"\",\"audio\":\"\",\"audioName\":\"\",\"hint\":\"\",\"index\":2,\"$$hashKey\":\"object:3009\"},{\"text\":\"3\",\"image\":\"\",\"audio\":\"\",\"audioName\":\"\",\"hint\":\"\",\"index\":3,\"$$hashKey\":\"object:3010\"}],\"optionsRHS\":[{\"text\":\"1\",\"image\":\"\",\"audio\":\"\",\"audioName\":\"\",\"hint\":\"\",\"mapIndex\":1},{\"text\":\"2\",\"image\":\"\",\"audio\":\"\",\"audioName\":\"\",\"hint\":\"\",\"mapIndex\":2},{\"text\":\"3\",\"image\":\"\",\"audio\":\"\",\"audioName\":\"\",\"hint\":\"\",\"mapIndex\":3}],\"questionCount\":0},\"media\":[]},\"config\":{\"metadata\":{\"max_score\":5,\"isShuffleOption\":false,\"isPartialScore\":true,\"templateType\":\"Horizontal\",\"name\":\"test2.1.8\\n\",\"title\":\"test2.1.8\\n\",\"gradeLevel\":[\"Class 3\"],\"subject\":\"Telugu\",\"medium\":\"Hindi\",\"board\":\"CBSE\",\"qlevel\":\"MEDIUM\",\"category\":\"MTF\"},\"max_time\":0,\"max_score\":1,\"partial_scoring\":true,\"layout\":\"Horizontal\",\"isShuffleOption\":false,\"questionCount\":1},\"media\":[]}}","createdOn":"2018-10-09T14:41:21.456+0000","gradeLevel":["Class 3"],"isShuffleOption":false,"appId":"prod.diksha.portal","lastUpdatedOn":"2018-10-09T14:41:21.456+0000","rhs_options":[{"value":{"type":"mixed","text":"इक","image":"","count":"","audio":"","resvalue":"इक","resindex":0},"index":0}],"identifier":"do_312608275099295744112219","consumerId":"0aa13c48-dda0-4259-9007-c795dacd7b9c","version":2,"versionKey":"1539096081456","lhs_options":[{"value":{"type":"mixed","text":"इक","image":"","count":"","audio":"","resvalue":"इक","resindex":0},"index":0}],"framework":"NCF","createdBy":"19abdacf-cb10-4d0b-a5c0-e68f2adb0a4c","max_score":5,"name":"test2.1.8\n","template_id":"NA","category":"MTF","board":"CBSE","status":"Live"}}}